tinymcp/__init__.py
tinymcp/registry.py
tinymcp/router.py
tinymcp-0.1.1.dist-info/METADATA
tinymcp-0.1.1.dist-info/WHEEL
tinymcp-0.1.1.dist-info/licenses/LICENSE
tinymcp-0.1.1.dist-info/RECORD
