Metadata-Version: 2.4
Name: tinymcp
Version: 0.1.1
Summary: A lightweight MCP router for FastAPI
Project-URL: Homepage, https://github.com/grab/tinymcp
Project-URL: Documentation, https://github.com/grab/tinymcp#readme
Project-URL: Repository, https://github.com/grab/tinymcp
Project-URL: Bug Tracker, https://github.com/grab/tinymcp/issues
Author-email: Md Riyadh <riyadh.sharif@grabtaxi.com>
Maintainer-email: Md Riyadh <riyadh.sharif@grabtaxi.com>, Felix Lie <felix.lie@grabtaxi.com>
License: MIT License
License-File: LICENSE
Keywords: api,fastapi,mcp,model-context-protocol,tools
Classifier: Development Status :: 4 - Beta
Classifier: Framework :: FastAPI
Classifier: Intended Audience :: Developers
Classifier: License :: OSI Approved :: MIT License
Classifier: Programming Language :: Python :: 3
Classifier: Programming Language :: Python :: 3.8
Classifier: Programming Language :: Python :: 3.9
Classifier: Programming Language :: Python :: 3.10
Classifier: Programming Language :: Python :: 3.11
Classifier: Programming Language :: Python :: 3.12
Classifier: Topic :: Software Development :: Libraries :: Python Modules
Requires-Python: >=3.8
Requires-Dist: fastapi>=0.68.0
